{
  "project_info": {
    "project_number": "33065506756",
    "firebase_url": "https://parcial2-c2912.firebaseio.com",
    "project_id": "parcial2-c2912",
    "storage_bucket": "parcial2-c2912.appspot.com"
  },
  "client": [
    {
      "client_info": {
        "mobilesdk_app_id": "1:33065506756:android:360ef52927efcdf1",
        "android_client_info": {
          "package_name": "com.example.and_x"
        }
      },
      "oauth_client": [
        {
          "client_id": "33065506756-k3s9et6v66gcteln63bg1f20vkjcnn9h.apps.googleusercontent.com",
          "client_type": 3
        }
      ],
      "api_key": [
        {
          "current_key": "AIzaSyB5BNxV6jHbZxLR8fdE7EUW6b5QhJzDEMI"
        }
      ],
      "services": {
        "appinvite_service": {
          "other_platform_oauth_client": [
            {
              "client_id": "33065506756-k3s9et6v66gcteln63bg1f20vkjcnn9h.apps.googleusercontent.com",
              "client_type": 3
            }
          ]
        }
      }
    },
    {
      "client_info": {
        "mobilesdk_app_id": "1:33065506756:android:a9de9caea1dc0a17",
        "android_client_info": {
          "package_name": "com.example.app_noti"
        }
      },
      "oauth_client": [
        {
          "client_id": "33065506756-k3s9et6v66gcteln63bg1f20vkjcnn9h.apps.googleusercontent.com",
          "client_type": 3
        }
      ],
      "api_key": [
        {
          "current_key": "AIzaSyB5BNxV6jHbZxLR8fdE7EUW6b5QhJzDEMI"
        }
      ],
      "services": {
        "appinvite_service": {
          "other_platform_oauth_client": [
            {
              "client_id": "33065506756-k3s9et6v66gcteln63bg1f20vkjcnn9h.apps.googleusercontent.com",
              "client_type": 3
            }
          ]
        }
      }
    }
  ],
  "configuration_version": "1"
}